LICENSE
setup.py
src/olympiad_data_structures/PointVector.py
src/olympiad_data_structures/__init__.py
src/olympiad_data_structures/main.py
src/olympiad_data_structures.egg-info/PKG-INFO
src/olympiad_data_structures.egg-info/SOURCES.txt
src/olympiad_data_structures.egg-info/dependency_links.txt
src/olympiad_data_structures.egg-info/requires.txt
src/olympiad_data_structures.egg-info/top_level.txt
src/olympiad_data_structures/number_theory/Eratosthenes_sieve.py
src/olympiad_data_structures/number_theory/__init__.py
src/olympiad_data_structures/number_theory/factorizer.py
src/olympiad_data_structures/number_theory/floor_log.py
src/olympiad_data_structures/number_theory/gcd_lcm.py
src/olympiad_data_structures/query_structures/__init__.py
src/olympiad_data_structures/query_structures/prefix_amounts.py
src/olympiad_data_structures/query_structures/sparse_table.py