Metadata-Version: 2.1
Name: olympiad_data_structures
Version: 0.0.11
License-File: LICENSE
Requires-Dist: bitarray
